hyper_connect/__init__.py
hyper_connect/_hyper_connect.py
hyper_connect/services/__init__.py
hyper_connect/services/_cache.py
hyper_connect/services/_data.py
hyper_connect/services/_info.py
hyper_connect/services/_queue.py
hyper_connect/services/_search.py
hyper_connect/services/_storage.py
hyper_connect/types/__init__.py
hyper_connect/types/_types.py
hyper_connect/utils/__init__.py
hyper_connect/utils/_create_hyper_request_params.py
hyper_connect/utils/_generate_token.py
hyper_connect/utils/_get_host.py
hyper_connect/utils/_get_key.py
hyper_connect/utils/_get_secret.py
hyper_connect/utils/_handle_response.py
hyper_connect/utils/_to_data_query.py
hyper_connect-0.0.10.dist-info/WHEEL
hyper_connect-0.0.10.dist-info/METADATA
hyper_connect-0.0.10.dist-info/RECORD
