Metadata-Version: 2.1
Name: hyper-connect
Version: 0.0.10
Summary: python SDK package for hyper
License: Apache 2.0
Author: Trip Ottinger
Requires-Python: >=3.8,<4.0
Classifier: License :: Other/Proprietary License
Classifier: Programming Language :: Python :: 3
Classifier: Programming Language :: Python :: 3.10
Classifier: Programming Language :: Python :: 3.8
Classifier: Programming Language :: Python :: 3.9
Requires-Dist: PyJWT (==2.3.0)
Requires-Dist: PyYAML (==6.0)
Requires-Dist: autopep8 (==1.6.0)
Requires-Dist: certifi (==2021.10.8)
Requires-Dist: cfgv (==3.3.1)
Requires-Dist: charset-normalizer (==2.0.12)
Requires-Dist: click (==8.1.3)
Requires-Dist: distlib (==0.3.4)
Requires-Dist: filelock (==3.6.0)
Requires-Dist: identify (==2.5.0)
Requires-Dist: idna (==3.3)
Requires-Dist: importlib-resources (==5.7.1)
Requires-Dist: numpy (==1.22.3)
Requires-Dist: pathspec (==0.9.0)
Requires-Dist: platformdirs (==2.5.2)
Requires-Dist: promisio (==0.1.1)
Requires-Dist: ramda (==0.7.4)
Requires-Dist: requests (==2.27.1)
Requires-Dist: requests-toolbelt (==0.9.1)
Requires-Dist: six (==1.16.0)
Requires-Dist: toml (==0.10.2)
Requires-Dist: tomli (==2.0.1)
Requires-Dist: toolz (==0.11.2)
Requires-Dist: typeguard (==2.13.3)
Requires-Dist: types-requests (==2.27.25)
Requires-Dist: types-urllib3 (==1.26.14)
Requires-Dist: typing-extensions (==4.2.0)
Requires-Dist: urllib3 (==1.26.9)
Requires-Dist: zipp (==3.8.0)
